MANIFEST.in
README.rst
setup.py
doc/Makefile
doc/__init__.py
doc/conf.py
doc/decorators.rst
doc/index.rst
doc/lck.cache.memoization.rst
doc/lck.concurrency.synchronization.rst
doc/lck.crypto.rst
doc/lck.files.rst
doc/lck.git.rst
doc/lck.lang.rst
doc/lck.math.rst
doc/lck.xml.rst
doc/license.rst
doc/make.bat
doc/overview.rst
doc/todo.rst
doc/theme/ADCtheme/LICENSE
doc/theme/ADCtheme/README.rst
doc/theme/ADCtheme/layout.html
doc/theme/ADCtheme/theme.conf
doc/theme/ADCtheme/static/adctheme.css
doc/theme/ADCtheme/static/breadcrumb_background.png
doc/theme/ADCtheme/static/documentation.png
doc/theme/ADCtheme/static/header_sm_mid.png
doc/theme/ADCtheme/static/scrn1.png
doc/theme/ADCtheme/static/scrn2.png
doc/theme/ADCtheme/static/searchfield_leftcap.png
doc/theme/ADCtheme/static/searchfield_repeat.png
doc/theme/ADCtheme/static/searchfield_rightcap.png
doc/theme/ADCtheme/static/title_background.png
doc/theme/ADCtheme/static/toc.js
doc/theme/ADCtheme/static/triangle_closed.png
doc/theme/ADCtheme/static/triangle_left.png
doc/theme/ADCtheme/static/triangle_open.png
src/lck/__init__.py
src/lck.common.egg-info/PKG-INFO
src/lck.common.egg-info/SOURCES.txt
src/lck.common.egg-info/dependency_links.txt
src/lck.common.egg-info/namespace_packages.txt
src/lck.common.egg-info/requires.txt
src/lck.common.egg-info/top_level.txt
src/lck.common.egg-info/zip-safe
src/lck/cache/__init__.py
src/lck/cache/memoization.py
src/lck/collections/__init__.py
src/lck/collections/orderedset.py
src/lck/concurrency/__init__.py
src/lck/concurrency/synchronization.py
src/lck/crypto/__init__.py
src/lck/crypto/cipher.py
src/lck/files/__init__.py
src/lck/files/finder.py
src/lck/git/__init__.py
src/lck/lang/__init__.py
src/lck/math/__init__.py
src/lck/math/elo_rating.py
src/lck/xml/__init__.py
src/lck/xml/converters.py
test/test_memoization.py
test/test_synchronization.py