Metadata-Version: 1.0
Name: lck.common
Version: 0.4.4
Summary: A library of various simple common routines that keep being rewritten all over again in every project I'm working on.
Home-page: http://packages.python.org/lck.common/
Author: Lukasz Langa
Author-email: lukasz@langa.pl
License: MIT
Platform: any
Classifier: Development Status :: 4 - Beta
Classifier: Intended Audience :: Developers
Classifier: License :: OSI Approved :: MIT License
Classifier: Natural Language :: English
Classifier: Operating System :: POSIX
Classifier: Operating System :: MacOS :: MacOS X
Classifier: Operating System :: Microsoft :: Windows :: Windows NT/2000
Classifier: Programming Language :: Python
Classifier: Programming Language :: Python :: 2.7
Classifier: Topic :: Software Development :: Libraries :: Python Modules
